django_jsonform/__init__.py
django_jsonform/admin.py
django_jsonform/apps.py
django_jsonform/constants.py
django_jsonform/exceptions.py
django_jsonform/tests.py
django_jsonform/urls.py
django_jsonform/utils.py
django_jsonform/validators.py
django_jsonform/views.py
django_jsonform/widgets.py
django_jsonform/forms/__init__.py
django_jsonform/forms/compat.py
django_jsonform/forms/fields.py
django_jsonform/models/__init__.py
django_jsonform/models/compat.py
django_jsonform/models/fields.py
django_jsonform/static/django_jsonform/index.js
django_jsonform/static/django_jsonform/react-json-form.js
django_jsonform/static/django_jsonform/style.css
django_jsonform/static/django_jsonform/img/arrow-icons.svg
django_jsonform/static/django_jsonform/img/collapsed-indicator-bg-dark.svg
django_jsonform/static/django_jsonform/img/collapsed-indicator-bg.svg
django_jsonform/static/django_jsonform/img/control-icons.svg
django_jsonform/static/django_jsonform/img/icon-addlink.svg
django_jsonform/static/django_jsonform/img/icon-changelink.svg
django_jsonform/static/django_jsonform/img/icon-deletelink.svg
django_jsonform/static/django_jsonform/vendor/react-dom.production.min.js
django_jsonform/static/django_jsonform/vendor/react-modal.min.js
django_jsonform/static/django_jsonform/vendor/react.production.min.js
django_jsonform/templates/django_jsonform/attrs.html
django_jsonform/templates/django_jsonform/editor.html
django_jsonform/templatetags/__init__.py
django_jsonform/templatetags/django_jsonform.py
tests/__init__.py
tests/__main__.py
tests/django_settings.py
tests/test_templatetags.py
tests/test_utils.py
tests/test_validators.py
tests/test_widgets.py
tests/models/__init__.py
tests/models/test_fields.py
django_jsonform-2.22.0.dist-info/LICENSE.txt
django_jsonform-2.22.0.dist-info/METADATA
django_jsonform-2.22.0.dist-info/WHEEL
django_jsonform-2.22.0.dist-info/top_level.txt
django_jsonform-2.22.0.dist-info/RECORD
